{"v":"4.8.0","meta":{"g":"LottieFiles AE 3.0.2","a":"","k":"","d":"","tc":""},"fr":29.9700012207031,"ip":0,"op":105.000004276738,"w":600,"h":400,"nm":"22.10.12) 태블릿 - 앞면 600*400 (문이 열리는 방식 수정 2)","ddd":0,"assets":[],"layers":[{"ddd":0,"ind":1,"ty":4,"nm":"트레이 흰 부분 윤곽선","sr":1,"ks":{"o":{"a":1,"k":[{"i":{"x":[0.833],"y":[0.833]},"o":{"x":[0.167],"y":[0.167]},"t":0,"s":[0]},{"t":15.0000006109625,"s":[100]}],"ix":11},"r":{"a":0,"k":0,"ix":10},"p":{"a":0,"k":[300,108.75,0],"ix":2},"a":{"a":0,"k":[474,5.5,0],"ix":1},"s":{"a":0,"k":[50.817,43.87,100],"ix":6}},"ao":0,"shapes":[{"ty":"gr","it":[{"ind":0,"ty":"sh","ix":1,"ks":{"a":0,"k":{"i":[[0,0],[0,0],[0,0],[0,0]],"o":[[0,0],[0,0],[0,0],[0,0]],"v":[[473.646,5.152],[-473.646,5.152],[-473.646,-5.152],[473.646,-5.152]],"c":true},"ix":2},"nm":"패스 1","mn":"ADBE Vector Shape - Group","hd":false},{"ty":"fl","c":{"a":0,"k":[1,0.999998743394,1,1],"ix":4},"o":{"a":0,"k":100,"ix":5},"r":1,"bm":0,"nm":"칠 1","mn":"ADBE Vector Graphic - Fill","hd":false},{"ty":"tr","p":{"a":0,"k":[473.896,5.402],"ix":2},"a":{"a":0,"k":[0,0],"ix":1},"s":{"a":0,"k":[100,100],"ix":3},"r":{"a":0,"k":0,"ix":6},"o":{"a":0,"k":100,"ix":7},"sk":{"a":0,"k":0,"ix":4},"sa":{"a":0,"k":0,"ix":5},"nm":"Transform"}],"nm":"그룹 1","np":2,"cix":2,"bm":0,"ix":1,"mn":"ADBE Vector Group","hd":false}],"ip":0,"op":105.000004276738,"st":0,"bm":0},{"ddd":0,"ind":3,"ty":4,"nm":"입구 조명 2 윤곽선","sr":1,"ks":{"o":{"a":1,"k":[{"i":{"x":[0.833],"y":[0.833]},"o":{"x":[0.167],"y":[0.167]},"t":57,"s":[0]},{"t":59.0000024031193,"s":[40]}],"ix":11},"r":{"a":0,"k":0,"ix":10},"p":{"a":0,"k":[301.125,153.875,0],"ix":2},"a":{"a":0,"k":[353,8,0],"ix":1},"s":{"a":1,"k":[{"i":{"x":[0.833,0.833,0.833],"y":[0.833,0.833,0.833]},"o":{"x":[0.167,0.167,0.167],"y":[0.167,0.167,0.167]},"t":59,"s":[41.4,43.87,100]},{"t":85.000003462121,"s":[49.2,43.87,100]}],"ix":6}},"ao":0,"shapes":[{"ty":"gr","it":[{"ind":0,"ty":"sh","ix":1,"ks":{"a":0,"k":{"i":[[0,0],[0,0],[0,0],[0,0]],"o":[[0,0],[0,0],[0,0],[0,0]],"v":[[352.994,-7.783],[352.994,7.783],[-352.994,7.783],[-352.994,-7.783]],"c":true},"ix":2},"nm":"패스 1","mn":"ADBE Vector Shape - Group","hd":false},{"ty":"gr","it":[{"ind":0,"ty":"sh","ix":1,"ks":{"a":0,"k":{"i":[[0,0],[0,0],[0,0],[0,0]],"o":[[0,0],[0,0],[0,0],[0,0]],"v":[[-543.246,639.928],[536.754,639.928],[536.754,-440.072],[-543.246,-440.072]],"c":true},"ix":2},"nm":"패스 1","mn":"ADBE Vector Shape - Group","hd":false},{"ind":1,"ty":"sh","ix":2,"ks":{"a":0,"k":{"i":[[0,0],[0,0],[0,0],[0,0]],"o":[[0,0],[0,0],[0,0],[0,0]],"v":[[-543.246,-440.072],[536.754,-440.072],[536.754,639.928],[-543.246,639.928]],"c":true},"ix":2},"nm":"패스 2","mn":"ADBE Vector Shape - Group","hd":false},{"ind":2,"ty":"sh","ix":3,"ks":{"a":0,"k":{"i":[[0,0],[0,0],[0,0],[0,0]],"o":[[0,0],[0,0],[0,0],[0,0]],"v":[[-352.994,7.783],[352.994,7.783],[352.994,-7.783],[-352.994,-7.783]],"c":true},"ix":2},"nm":"패스 3","mn":"ADBE Vector Shape - Group","hd":false},{"ind":3,"ty":"sh","ix":4,"ks":{"a":0,"k":{"i":[[0,0],[0,0],[0,0],[0,0]],"o":[[0,0],[0,0],[0,0],[0,0]],"v":[[-346.268,-7.783],[-352.994,7.783],[352.994,7.783],[346.82,-7.783]],"c":true},"ix":2},"nm":"패스 4","mn":"ADBE Vector Shape - Group","hd":false},{"ty":"tr","p":{"a":0,"k":[0,0],"ix":2},"a":{"a":0,"k":[0,0],"ix":1},"s":{"a":0,"k":[100,100],"ix":3},"r":{"a":0,"k":0,"ix":6},"o":{"a":0,"k":100,"ix":7},"sk":{"a":0,"k":0,"ix":4},"sa":{"a":0,"k":0,"ix":5},"nm":"Transform"}],"nm":"그룹 1","np":4,"cix":2,"bm":0,"ix":2,"mn":"ADBE Vector Group","hd":false},{"ty":"mm","mm":4,"nm":"패스 병합 1","mn":"ADBE Vector Filter - Merge","hd":false},{"ty":"fl","c":{"a":0,"k":[0.5,0.5,0.5,1],"ix":4},"o":{"a":0,"k":100,"ix":5},"r":1,"bm":0,"nm":"칠 1","mn":"ADBE Vector Graphic - Fill","hd":false},{"ty":"tr","p":{"a":0,"k":[352.994,7.783],"ix":2},"a":{"a":0,"k":[0,0],"ix":1},"s":{"a":0,"k":[100,100],"ix":3},"r":{"a":0,"k":0,"ix":6},"o":{"a":0,"k":100,"ix":7},"sk":{"a":0,"k":0,"ix":4},"sa":{"a":0,"k":0,"ix":5},"nm":"Transform"}],"nm":"그룹 1","np":4,"cix":2,"bm":0,"ix":1,"mn":"ADBE Vector Group","hd":false}],"ip":50.0000020365418,"op":105.000004276738,"st":10.0000004073083,"bm":0},{"ddd":0,"ind":5,"ty":4,"nm":"트레이 입구 열리는 문 2 윤곽선 2","td":1,"sr":1,"ks":{"o":{"a":0,"k":100,"ix":11},"r":{"a":0,"k":0,"ix":10},"p":{"a":0,"k":[300.081,135.06,0],"ix":2},"a":{"a":0,"k":[476.323,37.78,0],"ix":1},"s":{"a":0,"k":[49.826,40.651,100],"ix":6}},"ao":0,"shapes":[{"ty":"gr","it":[{"ind":0,"ty":"sh","ix":1,"ks":{"a":0,"k":{"i":[[5.612,0],[0,0],[0,-5.611],[0,0],[-5.611,0],[0,0],[0,5.612],[0,0]],"o":[[0,0],[-5.611,0],[0,0],[0,5.612],[0,0],[5.612,0],[0,0],[0,-5.611]],"v":[[465.896,-37.53],[-465.897,-37.53],[-476.073,-27.353],[-476.073,27.353],[-465.897,37.53],[465.896,37.53],[476.073,27.353],[476.073,-27.353]],"c":true},"ix":2},"nm":"패스 1","mn":"ADBE Vector Shape - Group","hd":false},{"ind":1,"ty":"sh","ix":2,"ks":{"a":0,"k":{"i":[[0,0],[0,-3.964],[0,0],[3.964,0],[0,0],[0,3.964],[0,0],[-3.964,0]],"o":[[3.964,0],[0,0],[0,3.964],[0,0],[-3.964,0],[0,0],[0,-3.964],[0,0]],"v":[[465.896,-34.53],[473.073,-27.353],[473.073,27.353],[465.896,34.53],[-465.897,34.53],[-473.073,27.353],[-473.073,-27.353],[-465.897,-34.53]],"c":true},"ix":2},"nm":"패스 2","mn":"ADBE Vector Shape - Group","hd":false},{"ty":"mm","mm":1,"nm":"패스 병합 1","mn":"ADBE Vector Filter - Merge","hd":false},{"ty":"fl","c":{"a":0,"k":[0.2415005553,0.218226548737,0.212319243188,1],"ix":4},"o":{"a":0,"k":100,"ix":5},"r":1,"bm":0,"nm":"칠 1","mn":"ADBE Vector Graphic - Fill","hd":false},{"ty":"tr","p":{"a":0,"k":[476.323,37.78],"ix":2},"a":{"a":0,"k":[0,0],"ix":1},"s":{"a":0,"k":[100,100],"ix":3},"r":{"a":0,"k":0,"ix":6},"o":{"a":0,"k":100,"ix":7},"sk":{"a":0,"k":0,"ix":4},"sa":{"a":0,"k":0,"ix":5},"nm":"Transform"}],"nm":"그룹 1","np":6,"cix":2,"bm":0,"ix":1,"mn":"ADBE Vector Group","hd":false},{"ty":"gr","it":[{"ind":0,"ty":"sh","ix":1,"ks":{"a":0,"k":{"i":[[0,0],[0,4.784],[0,0],[-4.785,0],[0,0],[0,-4.784],[0,0],[4.786,0]],"o":[[-4.785,0],[0,0],[0,-4.784],[0,0],[4.786,0],[0,0],[0,4.784],[0,0]],"v":[[-465.896,36.03],[-474.573,27.353],[-474.573,-27.353],[-465.896,-36.03],[465.896,-36.03],[474.573,-27.353],[474.573,27.353],[465.896,36.03]],"c":true},"ix":2},"nm":"패스 1","mn":"ADBE Vector Shape - Group","hd":false},{"ty":"fl","c":{"a":0,"k":[0.887487912646,0.886479097254,0.886039763806,1],"ix":4},"o":{"a":0,"k":100,"ix":5},"r":1,"bm":0,"nm":"칠 1","mn":"ADBE Vector Graphic - Fill","hd":false},{"ty":"tr","p":{"a":0,"k":[476.324,37.78],"ix":2},"a":{"a":0,"k":[0,0],"ix":1},"s":{"a":0,"k":[100,100],"ix":3},"r":{"a":0,"k":0,"ix":6},"o":{"a":0,"k":100,"ix":7},"sk":{"a":0,"k":0,"ix":4},"sa":{"a":0,"k":0,"ix":5},"nm":"Transform"}],"nm":"그룹 2","np":4,"cix":2,"bm":0,"ix":2,"mn":"ADBE Vector Group","hd":false}],"ip":15.0000006109625,"op":105.000004276738,"st":0,"bm":0},{"ddd":0,"ind":6,"ty":4,"nm":"트레이 입구 열리는 문 2 윤곽선","tt":2,"sr":1,"ks":{"o":{"a":1,"k":[{"i":{"x":[0.833],"y":[0.833]},"o":{"x":[0.167],"y":[0.167]},"t":5,"s":[0]},{"t":15.0000006109625,"s":[100]}],"ix":11},"r":{"a":0,"k":0,"ix":10},"p":{"a":1,"k":[{"i":{"x":0.667,"y":1},"o":{"x":0.333,"y":0},"t":25,"s":[300.081,164.06,0],"to":[0,-4.75,0],"ti":[0,4.75,0]},{"t":40.0000016292334,"s":[300.081,135.56,0]}],"ix":2},"a":{"a":0,"k":[476.323,37.78,0],"ix":1},"s":{"a":0,"k":[49.455,40.651,100],"ix":6}},"ao":0,"shapes":[{"ty":"gr","it":[{"ind":0,"ty":"sh","ix":1,"ks":{"a":0,"k":{"i":[[5.612,0],[0,0],[0,-5.611],[0,0],[-5.611,0],[0,0],[0,5.612],[0,0]],"o":[[0,0],[-5.611,0],[0,0],[0,5.612],[0,0],[5.612,0],[0,0],[0,-5.611]],"v":[[465.896,-37.53],[-465.897,-37.53],[-476.073,-27.353],[-476.073,27.353],[-465.897,37.53],[465.896,37.53],[476.073,27.353],[476.073,-27.353]],"c":true},"ix":2},"nm":"패스 1","mn":"ADBE Vector Shape - Group","hd":false},{"ind":1,"ty":"sh","ix":2,"ks":{"a":0,"k":{"i":[[0,0],[0,-3.964],[0,0],[3.964,0],[0,0],[0,3.964],[0,0],[-3.964,0]],"o":[[3.964,0],[0,0],[0,3.964],[0,0],[-3.964,0],[0,0],[0,-3.964],[0,0]],"v":[[465.896,-34.53],[473.073,-27.353],[473.073,27.353],[465.896,34.53],[-465.897,34.53],[-473.073,27.353],[-473.073,-27.353],[-465.897,-34.53]],"c":true},"ix":2},"nm":"패스 2","mn":"ADBE Vector Shape - Group","hd":false},{"ty":"mm","mm":1,"nm":"패스 병합 1","mn":"ADBE Vector Filter - Merge","hd":false},{"ty":"fl","c":{"a":0,"k":[0.2415005553,0.218226548737,0.212319243188,1],"ix":4},"o":{"a":0,"k":100,"ix":5},"r":1,"bm":0,"nm":"칠 1","mn":"ADBE Vector Graphic - Fill","hd":false},{"ty":"tr","p":{"a":0,"k":[476.323,37.78],"ix":2},"a":{"a":0,"k":[0,0],"ix":1},"s":{"a":0,"k":[100,100],"ix":3},"r":{"a":0,"k":0,"ix":6},"o":{"a":0,"k":100,"ix":7},"sk":{"a":0,"k":0,"ix":4},"sa":{"a":0,"k":0,"ix":5},"nm":"Transform"}],"nm":"그룹 1","np":6,"cix":2,"bm":0,"ix":1,"mn":"ADBE Vector Group","hd":false},{"ty":"gr","it":[{"ind":0,"ty":"sh","ix":1,"ks":{"a":0,"k":{"i":[[0,0],[0,4.784],[0,0],[-4.785,0],[0,0],[0,-4.784],[0,0],[4.786,0]],"o":[[-4.785,0],[0,0],[0,-4.784],[0,0],[4.786,0],[0,0],[0,4.784],[0,0]],"v":[[-465.896,36.03],[-474.573,27.353],[-474.573,-27.353],[-465.896,-36.03],[465.896,-36.03],[474.573,-27.353],[474.573,27.353],[465.896,36.03]],"c":true},"ix":2},"nm":"패스 1","mn":"ADBE Vector Shape - Group","hd":false},{"ty":"fl","c":{"a":0,"k":[0.887487912646,0.886479097254,0.886039763806,1],"ix":4},"o":{"a":0,"k":100,"ix":5},"r":1,"bm":0,"nm":"칠 1","mn":"ADBE Vector Graphic - Fill","hd":false},{"ty":"tr","p":{"a":0,"k":[476.324,37.78],"ix":2},"a":{"a":0,"k":[0,0],"ix":1},"s":{"a":0,"k":[100,100],"ix":3},"r":{"a":0,"k":0,"ix":6},"o":{"a":0,"k":100,"ix":7},"sk":{"a":0,"k":0,"ix":4},"sa":{"a":0,"k":0,"ix":5},"nm":"Transform"}],"nm":"그룹 2","np":4,"cix":2,"bm":0,"ix":2,"mn":"ADBE Vector Group","hd":false}],"ip":0,"op":105.000004276738,"st":0,"bm":0},{"ddd":0,"ind":9,"ty":4,"nm":"트레이 상단 마스크 용도 윤곽선","td":1,"sr":1,"ks":{"o":{"a":1,"k":[{"i":{"x":[0.833],"y":[0.833]},"o":{"x":[0.167],"y":[0.167]},"t":0,"s":[0]},{"t":15.0000006109625,"s":[100]}],"ix":11},"r":{"a":0,"k":0,"ix":10},"p":{"a":0,"k":[300,108.5,0],"ix":2},"a":{"a":0,"k":[475,83,0],"ix":1},"s":{"a":0,"k":[50.817,51.121,100],"ix":6}},"ao":0,"shapes":[{"ty":"gr","it":[{"ind":0,"ty":"sh","ix":1,"ks":{"a":0,"k":{"i":[[0,0],[0,0],[0,0],[0,0]],"o":[[0,0],[0,0],[0,0],[0,0]],"v":[[474.49,82.452],[-474.49,82.452],[-474.49,-82.452],[474.49,-82.452]],"c":true},"ix":2},"nm":"패스 1","mn":"ADBE Vector Shape - Group","hd":false},{"ty":"fl","c":{"a":0,"k":[0.886638327206,0.886244770125,0.887248140223,1],"ix":4},"o":{"a":0,"k":100,"ix":5},"r":1,"bm":0,"nm":"칠 1","mn":"ADBE Vector Graphic - Fill","hd":false},{"ty":"tr","p":{"a":0,"k":[474.74,82.702],"ix":2},"a":{"a":0,"k":[0,0],"ix":1},"s":{"a":0,"k":[100,100],"ix":3},"r":{"a":0,"k":0,"ix":6},"o":{"a":0,"k":100,"ix":7},"sk":{"a":0,"k":0,"ix":4},"sa":{"a":0,"k":0,"ix":5},"nm":"Transform"}],"nm":"그룹 1","np":2,"cix":2,"bm":0,"ix":1,"mn":"ADBE Vector Group","hd":false}],"ip":0,"op":105.000004276738,"st":0,"bm":0},{"ddd":0,"ind":10,"ty":4,"nm":"태블릿 윤곽선","tt":2,"sr":1,"ks":{"o":{"a":1,"k":[{"i":{"x":[0.833],"y":[0.833]},"o":{"x":[0.167],"y":[0.167]},"t":15,"s":[0]},{"t":40.0000016292334,"s":[100]}],"ix":11},"r":{"a":0,"k":0,"ix":10},"p":{"a":1,"k":[{"i":{"x":0.833,"y":0.833},"o":{"x":0.167,"y":0.167},"t":40,"s":[300,283,0],"to":[0,-19.917,0],"ti":[0,19.917,0]},{"t":85.000003462121,"s":[300,163.5,0]}],"ix":2},"a":{"a":0,"k":[462,202,0],"ix":1},"s":{"a":0,"k":[43.87,43.87,100],"ix":6}},"ao":0,"shapes":[{"ty":"gr","it":[{"ind":0,"ty":"sh","ix":1,"ks":{"a":0,"k":{"i":[[3.264,-1.885],[-3.243,-1.885],[-3.264,1.884],[3.253,1.891]],"o":[[-3.264,1.885],[3.253,1.89],[3.265,-1.885],[-3.243,-1.885]],"v":[[-5.872,-3.418],[-5.92,3.412],[5.88,3.412],[5.909,-3.418]],"c":true},"ix":2},"nm":"패스 1","mn":"ADBE Vector Shape - Group","hd":false},{"ty":"fl","c":{"a":0,"k":[0.39543540805,0.397023548799,0.398574589748,1],"ix":4},"o":{"a":0,"k":100,"ix":5},"r":1,"bm":0,"nm":"칠 1","mn":"ADBE Vector Graphic - Fill","hd":false},{"ty":"tr","p":{"a":0,"k":[128.606,130.178],"ix":2},"a":{"a":0,"k":[0,0],"ix":1},"s":{"a":0,"k":[100,100],"ix":3},"r":{"a":0,"k":0,"ix":6},"o":{"a":0,"k":100,"ix":7},"sk":{"a":0,"k":0,"ix":4},"sa":{"a":0,"k":0,"ix":5},"nm":"Transform"}],"nm":"그룹 1","np":4,"cix":2,"bm":0,"ix":1,"mn":"ADBE Vector Group","hd":false},{"ty":"gr","it":[{"ind":0,"ty":"sh","ix":1,"ks":{"a":0,"k":{"i":[[0.726,0],[0,0],[0.709,0.059],[-6.212,14.402],[0,0],[-0.408,0.995],[-7.523,0],[0,0],[-2.838,-6.857],[-0.837,-1.852],[0,0],[15.713,-1.297]],"o":[[0,0],[-0.727,0],[-15.631,-1.293],[0,0],[0.426,-0.988],[2.905,-7.09],[0,0],[7.547,0],[0.778,1.877],[0,0],[6.487,14.371],[-0.708,0.058]],"v":[[410.13,160.495],[-410.147,160.495],[-412.303,160.406],[-431.006,127.737],[-319.461,-145.793],[-318.216,-148.867],[-302.851,-160.495],[304.361,-160.495],[319.74,-148.621],[322.191,-143.112],[430.731,127.552],[412.281,160.407]],"c":true},"ix":2},"nm":"패스 1","mn":"ADBE Vector Shape - Group","hd":false},{"ty":"fl","c":{"a":0,"k":[0.962301216873,0.962664675245,0.96251077091,1],"ix":4},"o":{"a":0,"k":100,"ix":5},"r":1,"bm":0,"nm":"칠 1","mn":"ADBE Vector Graphic - Fill","hd":false},{"ty":"tr","p":{"a":0,"k":[464.881,177.759],"ix":2},"a":{"a":0,"k":[0,0],"ix":1},"s":{"a":0,"k":[100,100],"ix":3},"r":{"a":0,"k":0,"ix":6},"o":{"a":0,"k":100,"ix":7},"sk":{"a":0,"k":0,"ix":4},"sa":{"a":0,"k":0,"ix":5},"nm":"Transform"}],"nm":"그룹 2","np":4,"cix":2,"bm":0,"ix":2,"mn":"ADBE Vector Group","hd":false},{"ty":"gr","it":[{"ind":0,"ty":"sh","ix":1,"ks":{"a":0,"k":{"i":[[3.835,0],[0,0],[3.248,1.505],[-5.538,12.369],[0,0],[-1.279,3.07],[-7.34,0],[0,0],[-3.268,-7.118],[-1.355,-2.994],[0,0],[12.317,-5.689]],"o":[[0,0],[-3.846,0],[-12.296,-5.697],[0,0],[1.359,-3.036],[2.905,-6.972],[0,0],[7.365,0],[1.371,2.986],[0,0],[5.594,12.361],[-3.241,1.498]],"v":[[433.555,179.499],[-433.539,179.499],[-444.26,177.15],[-455.859,144.03],[-325.008,-158.788],[-320.937,-167.897],[-305.507,-179.499],[312.795,-179.499],[328.13,-167.897],[332.276,-158.842],[455.803,144.023],[444.249,177.163]],"c":true},"ix":2},"nm":"패스 1","mn":"ADBE Vector Shape - Group","hd":false},{"ty":"fl","c":{"a":0,"k":[0.214252965591,0.21388054642,0.213924602434,1],"ix":4},"o":{"a":0,"k":100,"ix":5},"r":1,"bm":0,"nm":"칠 1","mn":"ADBE Vector Graphic - Fill","hd":false},{"ty":"tr","p":{"a":0,"k":[461.647,179.75],"ix":2},"a":{"a":0,"k":[0,0],"ix":1},"s":{"a":0,"k":[100,100],"ix":3},"r":{"a":0,"k":0,"ix":6},"o":{"a":0,"k":100,"ix":7},"sk":{"a":0,"k":0,"ix":4},"sa":{"a":0,"k":0,"ix":5},"nm":"Transform"}],"nm":"그룹 3","np":4,"cix":2,"bm":0,"ix":3,"mn":"ADBE Vector Group","hd":false},{"ty":"gr","it":[{"ind":0,"ty":"sh","ix":1,"ks":{"a":0,"k":{"i":[[13.07,0],[0,0],[1.362,12.997],[0,0],[0,0],[0,0]],"o":[[0,0],[-13.069,0],[0,0],[0,0],[0,0],[-1.361,12.999]],"v":[[429.307,34.751],[-429.302,34.751],[-454.691,11.884],[-459.078,-34.751],[459.078,-34.751],[454.695,11.881]],"c":true},"ix":2},"nm":"패스 1","mn":"ADBE Vector Shape - Group","hd":false},{"ty":"fl","c":{"a":0,"k":[0.39543540805,0.397023548799,0.398574589748,1],"ix":4},"o":{"a":0,"k":100,"ix":5},"r":1,"bm":0,"nm":"칠 1","mn":"ADBE Vector Graphic - Fill","hd":false},{"ty":"tr","p":{"a":0,"k":[461.655,368.327],"ix":2},"a":{"a":0,"k":[0,0],"ix":1},"s":{"a":0,"k":[100,100],"ix":3},"r":{"a":0,"k":0,"ix":6},"o":{"a":0,"k":100,"ix":7},"sk":{"a":0,"k":0,"ix":4},"sa":{"a":0,"k":0,"ix":5},"nm":"Transform"}],"nm":"그룹 4","np":4,"cix":2,"bm":0,"ix":4,"mn":"ADBE Vector Group","hd":false}],"ip":0,"op":105.000004276738,"st":0,"bm":0},{"ddd":0,"ind":12,"ty":4,"nm":"레이어 8/태블릿_위(2차 수정) 윤곽선","sr":1,"ks":{"o":{"a":1,"k":[{"i":{"x":[0.833],"y":[0.833]},"o":{"x":[0.167],"y":[0.167]},"t":8,"s":[0]},{"t":15.0000006109625,"s":[100]}],"ix":11},"r":{"a":0,"k":0,"ix":10},"p":{"a":0,"k":[300,164,0],"ix":2},"a":{"a":0,"k":[473.5,35,0],"ix":1},"s":{"a":0,"k":[51.32,51.436,100],"ix":6}},"ao":0,"shapes":[{"ty":"gr","it":[{"ind":0,"ty":"sh","ix":1,"ks":{"a":0,"k":{"i":[[3.964,0],[0,0],[0,3.964],[0,0],[-3.964,0],[0,0],[0,-3.964],[0,0]],"o":[[0,0],[-3.964,0],[0,0],[0,-3.964],[0,0],[3.964,0],[0,0],[0,3.964]],"v":[[451.532,26.58],[-451.533,26.58],[-458.71,19.404],[-458.71,-19.403],[-451.533,-26.58],[451.532,-26.58],[458.709,-19.403],[458.709,19.404]],"c":true},"ix":2},"nm":"패스 1","mn":"ADBE Vector Shape - Group","hd":false},{"ty":"fl","c":{"a":0,"k":[0.2415005553,0.218226548737,0.212319243188,1],"ix":4},"o":{"a":0,"k":100,"ix":5},"r":1,"bm":0,"nm":"칠 1","mn":"ADBE Vector Graphic - Fill","hd":false},{"ty":"tr","p":{"a":0,"k":[472.904,34.896],"ix":2},"a":{"a":0,"k":[0,0],"ix":1},"s":{"a":0,"k":[100,100],"ix":3},"r":{"a":0,"k":0,"ix":6},"o":{"a":0,"k":100,"ix":7},"sk":{"a":0,"k":0,"ix":4},"sa":{"a":0,"k":0,"ix":5},"nm":"Transform"}],"nm":"그룹 1","np":4,"cix":2,"bm":0,"ix":1,"mn":"ADBE Vector Group","hd":false},{"ty":"gr","it":[{"ind":0,"ty":"sh","ix":1,"ks":{"a":0,"k":{"i":[[3.964,0],[0,0],[0,3.964],[0,0],[-3.964,0],[0,0],[0,-3.964],[0,0]],"o":[[0,0],[-3.964,0],[0,0],[0,-3.964],[0,0],[3.964,0],[0,0],[0,3.964]],"v":[[465.897,34.53],[-465.897,34.53],[-473.073,27.353],[-473.073,-27.353],[-465.897,-34.53],[465.897,-34.53],[473.074,-27.353],[473.074,27.353]],"c":true},"ix":2},"nm":"패스 1","mn":"ADBE Vector Shape - Group","hd":false},{"ty":"fl","c":{"a":0,"k":[0.39543540805,0.397023548799,0.398574589748,1],"ix":4},"o":{"a":0,"k":100,"ix":5},"r":1,"bm":0,"nm":"칠 1","mn":"ADBE Vector Graphic - Fill","hd":false},{"ty":"tr","p":{"a":0,"k":[473.323,34.78],"ix":2},"a":{"a":0,"k":[0,0],"ix":1},"s":{"a":0,"k":[100,100],"ix":3},"r":{"a":0,"k":0,"ix":6},"o":{"a":0,"k":100,"ix":7},"sk":{"a":0,"k":0,"ix":4},"sa":{"a":0,"k":0,"ix":5},"nm":"Transform"}],"nm":"그룹 2","np":4,"cix":2,"bm":0,"ix":2,"mn":"ADBE Vector Group","hd":false}],"ip":8.00000032584668,"op":105.000004276738,"st":0,"bm":0},{"ddd":0,"ind":14,"ty":4,"nm":"트레이 윤곽선","sr":1,"ks":{"o":{"a":1,"k":[{"i":{"x":[0.833],"y":[0.833]},"o":{"x":[0.167],"y":[0.167]},"t":0,"s":[0]},{"t":10.0000004073083,"s":[100]}],"ix":11},"r":{"a":0,"k":0,"ix":10},"p":{"a":0,"k":[300,200,0],"ix":2},"a":{"a":0,"k":[508.5,338.5,0],"ix":1},"s":{"a":0,"k":[51.54,51.54,100],"ix":6}},"ao":0,"shapes":[{"ty":"gr","it":[{"ind":0,"ty":"sh","ix":1,"ks":{"a":0,"k":{"i":[[12.795,0],[0,0],[0,12.795],[0,0],[-12.795,0],[0,0],[0,-12.795],[0,0]],"o":[[0,0],[-12.795,0],[0,0],[0,-12.795],[0,0],[12.795,0],[0,0],[0,12.795]],"v":[[484.591,338.184],[-484.591,338.184],[-507.758,315.017],[-507.758,-315.015],[-484.591,-338.184],[484.591,-338.184],[507.758,-315.015],[507.758,315.017]],"c":true},"ix":2},"nm":"패스 1","mn":"ADBE Vector Shape - Group","hd":false},{"ty":"fl","c":{"a":0,"k":[0.886638327206,0.886244770125,0.887248140223,1],"ix":4},"o":{"a":0,"k":100,"ix":5},"r":1,"bm":0,"nm":"칠 1","mn":"ADBE Vector Graphic - Fill","hd":false},{"ty":"tr","p":{"a":0,"k":[508.008,338.434],"ix":2},"a":{"a":0,"k":[0,0],"ix":1},"s":{"a":0,"k":[100,100],"ix":3},"r":{"a":0,"k":0,"ix":6},"o":{"a":0,"k":100,"ix":7},"sk":{"a":0,"k":0,"ix":4},"sa":{"a":0,"k":0,"ix":5},"nm":"Transform"}],"nm":"그룹 1","np":4,"cix":2,"bm":0,"ix":1,"mn":"ADBE Vector Group","hd":false}],"ip":0,"op":105.000004276738,"st":0,"bm":0}],"markers":[]}